Compiled from "SignaturePhrase.java"
class Monster implements HavingSignaturePhrase {
  java.lang.String mood;

  Monster();
    Code:
       0: aload_0       
       1: invokespecial #1                  // Method java/lang/Object."<init>":()V
       4: aload_0       
       5: ldc           #2                  // String angry
       7: putfield      #3                  // Field mood:Ljava/lang/String;
      10: return        
    LineNumberTable:
      line 15: 0
      line 16: 4

  public java.lang.String getMood();
    Code:
       0: aload_0       
       1: getfield      #3                  // Field mood:Ljava/lang/String;
       4: areturn       
    LineNumberTable:
      line 18: 0

  public java.lang.String getPhrase();
    Code:
       0: new           #4                  // class java/lang/StringBuilder
       3: dup           
       4: invokespecial #5                  // Method java/lang/StringBuilder."<init>":()V
       7: ldc           #6                  // String I'm 
       9: invokevirtual #7                  // Method java/lang/StringBuilder.append:(Ljava/lang/String;)Ljava/lang/StringBuilder;
      12: aload_0       
      13: invokevirtual #8                  // Method getMood:()Ljava/lang/String;
      16: invokevirtual #7                  // Method java/lang/StringBuilder.append:(Ljava/lang/String;)Ljava/lang/StringBuilder;
      19: ldc           #9                  // String !
      21: invokevirtual #7                  // Method java/lang/StringBuilder.append:(Ljava/lang/String;)Ljava/lang/StringBuilder;
      24: invokevirtual #10                 // Method java/lang/StringBuilder.toString:()Ljava/lang/String;
      27: areturn       
    LineNumberTable:
      line 21: 0
}
