Compiled from "SignaturePhrase.java"
class SignaturePhrase {
  SignaturePhrase();
    Code:
       0: aload_0       
       1: invokespecial #1                  // Method java/lang/Object."<init>":()V
       4: return        
    LineNumberTable:
      line 25: 0

  public static void say(HavingSignaturePhrase);
    Code:
       0: getstatic     #2                  // Field java/lang/System.out:Ljava/io/PrintStream;
       3: aload_0       
       4: invokeinterface #3,  1            // InterfaceMethod HavingSignaturePhrase.getPhrase:()Ljava/lang/String;
       9: invokevirtual #4                  // Method java/io/PrintStream.println:(Ljava/lang/String;)V
      12: return        
    LineNumberTable:
      line 27: 0
      line 28: 12

  public static void main(java.lang.String[]);
    Code:
       0: new           #5                  // class Player
       3: dup           
       4: invokespecial #6                  // Method Player."<init>":()V
       7: astore_1      
       8: new           #7                  // class Monster
      11: dup           
      12: invokespecial #8                  // Method Monster."<init>":()V
      15: astore_2      
      16: aload_1       
      17: invokestatic  #9                  // Method say:(LHavingSignaturePhrase;)V
      20: aload_2       
      21: invokestatic  #9                  // Method say:(LHavingSignaturePhrase;)V
      24: return        
    LineNumberTable:
      line 30: 0
      line 31: 8
      line 32: 16
      line 33: 20
      line 34: 24
}
