Compiled from "Escaped.java"
public class Escaped {
  public Escaped();
    Code:
       0: aload_0       
       1: invokespecial #1                  // Method java/lang/Object."<init>":()V
       4: return        
    LineNumberTable:
      line 1: 0

  public java.lang.String addSome(java.lang.String);
    Code:
       0: new           #2                  // class java/lang/StringBuilder
       3: dup           
       4: invokespecial #3                  // Method java/lang/StringBuilder."<init>":()V
       7: ldc           #4                  // String hoge(\"
       9: invokevirtual #5                  // Method java/lang/StringBuilder.append:(Ljava/lang/String;)Ljava/lang/StringBuilder;
      12: aload_1       
      13: invokevirtual #5                  // Method java/lang/StringBuilder.append:(Ljava/lang/String;)Ljava/lang/StringBuilder;
      16: ldc           #6                  // String \");
      18: invokevirtual #5                  // Method java/lang/StringBuilder.append:(Ljava/lang/String;)Ljava/lang/StringBuilder;
      21: invokevirtual #7                  // Method java/lang/StringBuilder.toString:()Ljava/lang/String;
      24: areturn       
    LineNumberTable:
      line 3: 0
}
